setup.cfg
setup.py
exploratory_analysis/Data_Analysis.py
exploratory_analysis/__init__.py
exploratory_analysis.egg-info/PKG-INFO
exploratory_analysis.egg-info/SOURCES.txt
exploratory_analysis.egg-info/dependency_links.txt
exploratory_analysis.egg-info/top_level.txt