Metadata-Version: 2.1
Name: exploratory-analysis
Version: 1.0.0
Summary: Exploratory Data Analysis
Author: Abhilash Maspalli Srinivas
Author-email: <abhilash_maspallisrinivas@comcast.com>
License: UNKNOWN
Keywords: python,EDA,PDF
Platform: UNKNOWN
Classifier: Intended Audience :: Education
Classifier: Programming Language :: Python :: 3
Classifier: License :: OSI Approved :: MIT License
Classifier: Operating System :: OS Independent
